alphaess/__init__.py
alphaess/alphaess.py
alphaessopenapi-0.0.16.dist-info/licenses/LICENSE
alphaessopenapi-0.0.16.dist-info/METADATA
alphaessopenapi-0.0.16.dist-info/WHEEL
alphaessopenapi-0.0.16.dist-info/top_level.txt
alphaessopenapi-0.0.16.dist-info/RECORD
