Metadata-Version: 2.4
Name: alphaessopenapi
Version: 0.0.16
Summary: A python library to retrieve energy statistics from your Alpha ESS inverter by polling the Official Alpha ESS Open API.
Home-page: https://github.com/CharlesGillanders/alphaess-openAPI
Author: Charles Gillanders
Author-email: charles@charlesgillanders.com
Classifier: Programming Language :: Python :: 3
Classifier: License :: OSI Approved :: MIT License
Classifier: Operating System :: OS Independent
License-File: LICENSE
Dynamic: author
Dynamic: author-email
Dynamic: classifier
Dynamic: description
Dynamic: description-content-type
Dynamic: home-page
Dynamic: license-file
Dynamic: summary
